odoo/addons/l10n_it_reverse_charge_start_end_dates/README.rst
odoo/addons/l10n_it_reverse_charge_start_end_dates/__init__.py
odoo/addons/l10n_it_reverse_charge_start_end_dates/__manifest__.py
odoo/addons/l10n_it_reverse_charge_start_end_dates/i18n/it.po
odoo/addons/l10n_it_reverse_charge_start_end_dates/i18n/l10n_it_reverse_charge_start_end_dates.pot
odoo/addons/l10n_it_reverse_charge_start_end_dates/models/__init__.py
odoo/addons/l10n_it_reverse_charge_start_end_dates/models/account_move.py
odoo/addons/l10n_it_reverse_charge_start_end_dates/readme/CONTRIBUTORS.md
odoo/addons/l10n_it_reverse_charge_start_end_dates/readme/DESCRIPTION.md
odoo/addons/l10n_it_reverse_charge_start_end_dates/static/description/icon.png
odoo/addons/l10n_it_reverse_charge_start_end_dates/static/description/index.html
odoo14_addon_l10n_it_reverse_charge_start_end_dates-14.0.1.0.1.dev4.dist-info/METADATA
odoo14_addon_l10n_it_reverse_charge_start_end_dates-14.0.1.0.1.dev4.dist-info/WHEEL
odoo14_addon_l10n_it_reverse_charge_start_end_dates-14.0.1.0.1.dev4.dist-info/top_level.txt
odoo14_addon_l10n_it_reverse_charge_start_end_dates-14.0.1.0.1.dev4.dist-info/RECORD
