Metadata-Version: 2.1
Name: odoo14-addon-l10n_it_reverse_charge_start_end_dates
Version: 14.0.1.0.1.dev4
Requires-Python: >=3.6
Requires-Dist: odoo14-addon-account_invoice_start_end_dates
Requires-Dist: odoo14-addon-l10n_it_reverse_charge
Requires-Dist: odoo>=14.0a,<14.1dev
Summary: Gestione delle date di competenza per le autofatture in reverse charge
Home-page: https://github.com/OCA/l10n-italy
License: AGPL-3
Author: Innovyou, Odoo Community Association (OCA)
Author-email: support@odoo-community.org
Classifier: Programming Language :: Python
Classifier: Framework :: Odoo
Classifier: Framework :: Odoo :: 14.0
Classifier: License :: OSI Approved :: GNU Affero General Public License v3
